PyShaping/__init__.py
pyshaping-2.3.2.dist-info/METADATA
pyshaping-2.3.2.dist-info/WHEEL
pyshaping-2.3.2.dist-info/licenses/LICENSE
pyshaping-2.3.2.dist-info/RECORD
