Metadata-Version: 2.4
Name: PyShaping
Version: 2.3.2
Summary: Math functions for 2D and 3D shapes
Project-URL: Homepage, https://github.com/Albair581/PyShaping
Project-URL: Issues, https://github.com/Albair581/PyShaping/issues
Author-email: Albert Huang <albertoyucheng@gmail.com>
License-File: LICENSE
Classifier: License :: OSI Approved :: GNU General Public License v3 (GPLv3)
Classifier: Operating System :: OS Independent
Classifier: Programming Language :: Python :: 3
Requires-Python: >=3.0
